{"stat.walkOneCm":81262,"stat.craftItem.minecraft.bed":1,"stat.playerKills":2,"stat.entityKilledBy.Spider":1,"stat.useItem.minecraft.bed":1,"achievement.openInventory":4,"stat.craftItem.minecraft.planks":36,"stat.craftItem.minecraft.stone_axe":1,"stat.leaveGame":1,"stat.damageTaken":760,"stat.killEntity.Spider":1,"stat.craftItem.minecraft.crafting_table":2,"stat.craftItem.minecraft.stone_pickaxe":1,"stat.useItem.minecraft.wooden_pickaxe":22,"stat.mobKills":4,"stat.craftItem.minecraft.wooden_sword":2,"stat.mineBlock.minecraft.log":9,"stat.craftItem.minecraft.stone_sword":1,"stat.flyOneCm":2689,"stat.deaths":2,"stat.useItem.minecraft.mutton":4,"stat.jump":112,"stat.swimOneCm":1554,"stat.mineBlock.minecraft.leaves":13,"stat.playOneMinute":35497,"stat.entityKilledBy.Zombie":1,"stat.fallOneCm":2234,"stat.useItem.minecraft.wooden_sword":19,"stat.killEntity.Sheep":3,"stat.damageDealt":1150,"stat.timeSinceDeath":8131,"stat.sprintOneCm":159,"stat.mineBlock.minecraft.dirt":2,"stat.useItem.minecraft.crafting_table":2,"stat.craftItem.minecraft.wooden_pickaxe":1,"stat.mineBlock.minecraft.stone":22,"achievement.exploreAllBiomes":{"value":0,"progress":["ForestHills","River","Plains"]},"stat.mineBlock.minecraft.tallgrass":16,"stat.diveOneCm":542,"stat.craftItem.minecraft.stick":16,"stat.craftingTableInteraction":3}